AUTHORS.rst
CONTRIBUTING.rst
HISTORY.rst
LICENSE
MANIFEST.in
README.rst
requirements.txt
requirements_dev.txt
setup.cfg
setup.py
docs/Makefile
docs/authors.rst
docs/conf.py
docs/contributing.rst
docs/development.rst
docs/index.rst
docs/installation.rst
docs/make.bat
docs/modules.rst
docs/proxysql_tools.aws.rst
docs/proxysql_tools.galera.rst
docs/proxysql_tools.proxysql.rst
docs/proxysql_tools.rst
docs/readme.rst
docs/usage.rst
proxysql_tools/__init__.py
proxysql_tools/cli.py
proxysql_tools/load_balancing_mode.py
proxysql_tools.egg-info/PKG-INFO
proxysql_tools.egg-info/SOURCES.txt
proxysql_tools.egg-info/dependency_links.txt
proxysql_tools.egg-info/entry_points.txt
proxysql_tools.egg-info/not-zip-safe
proxysql_tools.egg-info/requires.txt
proxysql_tools.egg-info/top_level.txt
proxysql_tools/aws/__init__.py
proxysql_tools/aws/aws.py
proxysql_tools/cli_entrypoint/__init__.py
proxysql_tools/cli_entrypoint/galera.py
proxysql_tools/galera/__init__.py
proxysql_tools/galera/exceptions.py
proxysql_tools/galera/galera_cluster.py
proxysql_tools/galera/galera_node.py
proxysql_tools/galera/server.py
proxysql_tools/galera/user.py
proxysql_tools/proxysql/__init__.py
proxysql_tools/proxysql/exceptions.py
proxysql_tools/proxysql/proxysql.py
proxysql_tools/util/__init__.py
proxysql_tools/util/bug1258464.py
tests/__init__.py
tests/development/__init__.py
tests/development/conftest.py
tests/development/galera/__init__.py
tests/development/galera/test_galera_cluster.py
tests/development/galera/test_galera_node.py
tests/development/proxysql/__init__.py
tests/development/proxysql/test_proxysql.py
tests/integration/__init__.py
tests/integration/conftest.py
tests/integration/library.py
tests/integration/test_cli.py
tests/unit/conftest.py
tests/unit/test_aws.py
tests/unit/test_util.py
tests/unit/galera/__init__.py
tests/unit/galera/conftest.py
tests/unit/galera/test_galera_cluster.py
tests/unit/galera/test_galera_node.py
tests/unit/galera/test_galera_server.py
tests/unit/galera/test_galera_user.py
tests/unit/proxysql/__init__.py
tests/unit/proxysql/conftest.py
tests/unit/proxysql/test_proxysql.py