Metadata-Version: 1.1
Name: proxysql-tools
Version: 0.3.12
Summary: ProxySQL Tools
Home-page: https://github.com/twindb/proxysql-tools
Author: TwinDB Development Team
Author-email: dev@twindb.com
License: Apache Software License 2.0
Keywords: proxysql_tools
Platform: UNKNOWN
Classifier: Development Status :: 2 - Pre-Alpha
Classifier: Intended Audience :: Developers
Classifier: License :: OSI Approved :: Apache Software License
Classifier: Natural Language :: English
Classifier: Programming Language :: Python :: 2
Classifier: Programming Language :: Python :: 2.7
